fetch_user/__init__.py
fetch_user/setup.py
fetch_user-0.0.2.dist-info/METADATA
fetch_user-0.0.2.dist-info/WHEEL
fetch_user-0.0.2.dist-info/top_level.txt
fetch_user-0.0.2.dist-info/RECORD
