Metadata-Version: 2.1
Name: fetch-user
Version: 0.0.2
Summary: Python Disord API wrapper for fetching users by ID
Home-page: https://github.com
Author: pkguploaders
Author-email: example@example.com
License: UNKNOWN
Platform: UNKNOWN
Classifier: Programming Language :: Python :: 3
Classifier: License :: OSI Approved :: MIT License
Classifier: Operating System :: OS Independent
Requires-Python: >=3.6
